typing_test/__init__.py
typing_test/cli.py
typing_test/input_sentences.txt
typing_test/typing_test.py
typing_test_sapien-3.0.2.dist-info/LICENSE
typing_test_sapien-3.0.2.dist-info/METADATA
typing_test_sapien-3.0.2.dist-info/WHEEL
typing_test_sapien-3.0.2.dist-info/entry_points.txt
typing_test_sapien-3.0.2.dist-info/top_level.txt
typing_test_sapien-3.0.2.dist-info/RECORD
