Metadata-Version: 2.1
Name: typing-test-sapien
Version: 3.0.2
Summary: A CLI-based typing speed test application
Home-page: https://github.com/prasad-sdh/typing_test.git
Author: Prasad SDH
Author-email: prasad@audiomob.com
Classifier: Programming Language :: Python :: 3
Classifier: License :: OSI Approved :: MIT License
Classifier: Operating System :: OS Independent
Requires-Python: >=3.1
License-File: LICENSE
